sparsepixels/__init__.py
sparsepixels/layers.py
sparsepixels/img/logo.png
sparsepixels-0.1.0.dist-info/licenses/LICENSE
sparsepixels-0.1.0.dist-info/METADATA
sparsepixels-0.1.0.dist-info/WHEEL
sparsepixels-0.1.0.dist-info/top_level.txt
sparsepixels-0.1.0.dist-info/RECORD
