Metadata-Version: 2.4
Name: sparsepixels
Version: 0.1.0
Summary: Efficient convolution for sparse data on FPGAs
Home-page: https://github.com/hftsoi/sparse-pixels
Author: Ho Fung Tsoi
Author-email: ho.fung.tsoi@cern.ch
License: MIT
Classifier: Programming Language :: Python :: 3
Classifier: License :: OSI Approved :: MIT License
Requires-Python: >=3.10
License-File: LICENSE
Requires-Dist: tensorflow<2.15.0,>=2.14.0
Requires-Dist: keras<2.15.0,>=2.14.0
Requires-Dist: qkeras<0.10.0,>=0.9.0
Dynamic: license-file
